{
  "__className__": "serverpod.DatabaseMigration",
  "actions": [
    {
      "__className__": "serverpod.DatabaseMigrationAction",
      "type": "alterTable",
      "alterTable": {
        "__className__": "serverpod.TableMigration",
        "name": "stop",
        "schema": "public",
        "addColumns": [
          {
            "__className__": "serverpod.ColumnDefinition",
            "name": "_tripStopsTripId",
            "columnType": 6,
            "isNullable": true,
            "dartType": "int?"
          }
        ],
        "deleteColumns": [
          "stopId"
        ],
        "modifyColumns": [],
        "addIndexes": [],
        "deleteIndexes": [],
        "addForeignKeys": [
          {
            "__className__": "serverpod.ForeignKeyDefinition",
            "constraintName": "stop_fk_0",
            "columns": [
              "_tripStopsTripId"
            ],
            "referenceTable": "trip",
            "referenceTableSchema": "public",
            "referenceColumns": [
              "id"
            ],
            "onUpdate": 3,
            "onDelete": 3
          }
        ],
        "deleteForeignKeys": [],
        "warnings": [
          {
            "__className__": "serverpod.DatabaseMigrationWarning",
            "type": "columnDropped",
            "message": "Column \"stopId\" of table \"stop\" will be dropped.",
            "table": "stop",
            "columns": [
              "stopId"
            ],
            "destrucive": true
          }
        ]
      }
    },
    {
      "__className__": "serverpod.DatabaseMigrationAction",
      "type": "deleteTable",
      "deleteTable": "trip"
    },
    {
      "__className__": "serverpod.DatabaseMigrationAction",
      "type": "createTable",
      "createTable": {
        "__className__": "serverpod.TableDefinition",
        "name": "trip",
        "dartName": "Trip",
        "module": "road_trip_butler",
        "schema": "public",
        "columns": [
          {
            "__className__": "serverpod.ColumnDefinition",
            "name": "id",
            "columnType": 6,
            "isNullable": false,
            "columnDefault": "nextval('trip_id_seq'::regclass)",
            "dartType": "int?"
          },
          {
            "__className__": "serverpod.ColumnDefinition",
            "name": "description",
            "columnType": 0,
            "isNullable": false,
            "dartType": "String"
          },
          {
            "__className__": "serverpod.ColumnDefinition",
            "name": "startAddress",
            "columnType": 0,
            "isNullable": false,
            "dartType": "String"
          },
          {
            "__className__": "serverpod.ColumnDefinition",
            "name": "endAddress",
            "columnType": 0,
            "isNullable": false,
            "dartType": "String"
          },
          {
            "__className__": "serverpod.ColumnDefinition",
            "name": "departureTime",
            "columnType": 4,
            "isNullable": false,
            "dartType": "DateTime"
          },
          {
            "__className__": "serverpod.ColumnDefinition",
            "name": "personality",
            "columnType": 0,
            "isNullable": false,
            "dartType": "String"
          },
          {
            "__className__": "serverpod.ColumnDefinition",
            "name": "polyline",
            "columnType": 0,
            "isNullable": true,
            "dartType": "String?"
          },
          {
            "__className__": "serverpod.ColumnDefinition",
            "name": "preferences",
            "columnType": 0,
            "isNullable": true,
            "dartType": "String?"
          },
          {
            "__className__": "serverpod.ColumnDefinition",
            "name": "totalDurationSeconds",
            "columnType": 6,
            "isNullable": true,
            "dartType": "int?"
          }
        ],
        "foreignKeys": [],
        "indexes": [
          {
            "__className__": "serverpod.IndexDefinition",
            "indexName": "trip_pkey",
            "elements": [
              {
                "__className__": "serverpod.IndexElementDefinition",
                "type": 0,
                "definition": "id"
              }
            ],
            "type": "btree",
            "isUnique": true,
            "isPrimary": true
          }
        ],
        "managed": true
      }
    }
  ],
  "warnings": [
    {
      "__className__": "serverpod.DatabaseMigrationWarning",
      "type": "columnDropped",
      "message": "Column \"stopId\" of table \"stop\" will be dropped.",
      "table": "stop",
      "columns": [
        "stopId"
      ],
      "destrucive": true
    },
    {
      "__className__": "serverpod.DatabaseMigrationWarning",
      "type": "columnDropped",
      "message": "Column \"stops\" of table \"trip\" will be dropped.",
      "table": "trip",
      "columns": [
        "stops"
      ],
      "destrucive": true
    },
    {
      "__className__": "serverpod.DatabaseMigrationWarning",
      "type": "tableDropped",
      "message": "One or more columns are added to table \"trip\" which cannot be added in a table migration. The complete table will be deleted and recreated.",
      "table": "trip",
      "columns": [
        "personality"
      ],
      "destrucive": true
    }
  ],
  "migrationApiVersion": 1
}